odoo/addons/shopinvader_locomotive/README.rst
odoo/addons/shopinvader_locomotive/__init__.py
odoo/addons/shopinvader_locomotive/__manifest__.py
odoo/addons/shopinvader_locomotive/component/__init__.py
odoo/addons/shopinvader_locomotive/component/adapter.py
odoo/addons/shopinvader_locomotive/component/binder.py
odoo/addons/shopinvader_locomotive/component/core.py
odoo/addons/shopinvader_locomotive/component/deleter.py
odoo/addons/shopinvader_locomotive/component/event_listeners.py
odoo/addons/shopinvader_locomotive/component/exporter.py
odoo/addons/shopinvader_locomotive/component/mapper.py
odoo/addons/shopinvader_locomotive/component/shopinvader_partner_adapter.py
odoo/addons/shopinvader_locomotive/component/shopinvader_partner_export_mapper.py
odoo/addons/shopinvader_locomotive/component/shopinvader_site_export_mapper.py
odoo/addons/shopinvader_locomotive/controllers/__init__.py
odoo/addons/shopinvader_locomotive/controllers/main.py
odoo/addons/shopinvader_locomotive/data/ir_cron.xml
odoo/addons/shopinvader_locomotive/demo/backend_demo.xml
odoo/addons/shopinvader_locomotive/models/__init__.py
odoo/addons/shopinvader_locomotive/models/locomotive_binding.py
odoo/addons/shopinvader_locomotive/models/res_partner.py
odoo/addons/shopinvader_locomotive/models/shopinvader_backend.py
odoo/addons/shopinvader_locomotive/models/shopinvader_partner.py
odoo/addons/shopinvader_locomotive/readme/CONFIGURE.rst
odoo/addons/shopinvader_locomotive/readme/CONTRIBUTORS.rst
odoo/addons/shopinvader_locomotive/readme/DESCRIPTION.rst
odoo/addons/shopinvader_locomotive/readme/HISTORY.rst
odoo/addons/shopinvader_locomotive/readme/ROADMAP.rst
odoo/addons/shopinvader_locomotive/services/__init__.py
odoo/addons/shopinvader_locomotive/services/customer.py
odoo/addons/shopinvader_locomotive/static/description/icon.png
odoo/addons/shopinvader_locomotive/static/description/index.html
odoo/addons/shopinvader_locomotive/tests/__init__.py
odoo/addons/shopinvader_locomotive/tests/common.py
odoo12_addon_shopinvader_locomotive-12.0.3.3.0.dist-info/METADATA
odoo12_addon_shopinvader_locomotive-12.0.3.3.0.dist-info/WHEEL
odoo12_addon_shopinvader_locomotive-12.0.3.3.0.dist-info/top_level.txt
odoo12_addon_shopinvader_locomotive-12.0.3.3.0.dist-info/RECORD
