Metadata-Version: 2.1
Name: odoo12-addon-shopinvader-locomotive
Version: 12.0.3.3.0
Summary: Manage communications between Shopinvader and Locomotive CMS
Home-page: https://github.com/shopinvader/odoo-shopinvader
Author: Akretion
License: AGPL-3
Platform: UNKNOWN
Classifier: Programming Language :: Python
Classifier: Framework :: Odoo
Classifier: License :: OSI Approved :: GNU Affero General Public License v3
Requires-Python: >=3.5
Requires-Dist: locomotivecms
Requires-Dist: odoo12-addon-base-suspend-security
Requires-Dist: odoo12-addon-connector
Requires-Dist: odoo12-addon-queue-job
Requires-Dist: odoo12-addon-shopinvader
Requires-Dist: odoo12-addon-shopinvader-search-engine
Requires-Dist: odoo (<12.1dev,>=12.0a)
